README.rst
setup.py
mystiko/__init__.py
mystiko/k8s.py
mystiko.egg-info/PKG-INFO
mystiko.egg-info/SOURCES.txt
mystiko.egg-info/dependency_links.txt
mystiko.egg-info/not-zip-safe
mystiko.egg-info/pbr.json
mystiko.egg-info/top_level.txt