Metadata-Version: 1.0
Name: mystiko
Version: 0.2
Summary: Collect Kubernetes secrets into a python dictionary.
Home-page: http://github.com/lander2k2/mystiko
Author: Richard Lander
Author-email: lander2k2@gmail.com
License: MIT
Platform: UNKNOWN
